{
     "context": {
       "action": "on_search",
       "bap_id": "ondc-bob.azurewebsites.net",
       "bap_uri": "https://ondc-bob.azurewebsites.net",
       "domain": "ONDC:TRV10",
       "location": {
         "city": {
           "code": "std:080"
         },
         "country": {
           "code": "IND"
         }
       },
       "message_id": "60a906a8-37b3-4abb-95db-505a377918d5",
       "timestamp": "2025-05-06T17:26:52.515Z",
       "transaction_id": "db073986-373e-464e-96b9-2ceeb128d6f9",
       "ttl": "PT30S",
       "version": "2.0.1",
       "bpp_id": "pramaan.ondc.org/beta/preprod/mock/seller",
       "bpp_uri": "https://pramaan.ondc.org/beta/preprod/mock/seller"
     },
     "message": {
       "catalog": {
         "descriptor": {
           "name": "ONDC Pramaan Ride Services"
         },
         "providers": [
           {
             "id": "OD_101",
             "fulfillments": [
               {
                 "id": "f95cdf28-1627-432a-b3a8-43ed3b537262",
                 "stops": [
                   {
                     "location": {
                       "gps": "12.935549,77.605885"
                     },
                     "type": "START",
                     "instructions": {
                       "short_desc": "Information about location",
                       "long_desc": "Information about location"
                     }
                   },
                   {
                     "location": {
                       "gps": "12.935010,77.573460"
                     },
                     "type": "END"
                   }
                 ],
                 "type": "DELIVERY",
                 "vehicle": {
                   "category": "CAB",
                   "variant": "SUV",
                   "energy_type": "CNG"
                 }
               },
               {
                 "id": "ae10ca31-d6da-498d-ae67-b1e7aea9523b",
                 "stops": [
                   {
                     "location": {
                       "gps": "12.935549,77.605885"
                     },
                     "type": "START",
                     "instructions": {
                       "short_desc": "Information about location",
                       "long_desc": "Information about location"
                     }
                   },
                   {
                     "location": {
                       "gps": "12.935010,77.573460"
                     },
                     "type": "END"
                   }
                 ],
                 "type": "DELIVERY",
                 "vehicle": {
                   "category": "AUTO_RICKSHAW",
                   "variant": "AUTO_RICKSHAW",
                   "energy_type": "ELECTRIC"
                 }
               },
               {
                 "id": "2efcc00a-9ef9-487e-b927-a4d34207de36",
                 "stops": [
                   {
                     "location": {
                       "gps": "12.935549,77.605885"
                     },
                     "type": "START",
                     "instructions": {
                       "short_desc": "Information about location",
                       "long_desc": "Information about location"
                     }
                   },
                   {
                     "location": {
                       "gps": "12.935010,77.573460"
                     },
                     "type": "END"
                   }
                 ],
                 "type": "DELIVERY",
                 "vehicle": {
                   "category": "TWO_WHEELER",
                   "variant": "TWO_WHEELER",
                   "energy_type": "DIESEL"
                 }
               }
             ],
             "items": [
               {
                 "id": "I1",
                 "descriptor": {
                   "code": "RIDE",
                   "name": "Cab Ride"
                 },
                 "fulfillment_ids": [
                   "f95cdf28-1627-432a-b3a8-43ed3b537262"
                 ],
                 "price": {
                   "currency": "INR",
                   "value": "210.00",
                   "minimum_value": "190",
                   "maximum_value": "230"
                 },
                 "location_ids": [
                   "4eef859d-67c7-4c9a-9739-b3a81aa69c34",
                   "4dfa6bfa-5ccf-492e-b2f8-3bf1939dcd88"
                 ]
               },
               {
                 "id": "I2",
                 "descriptor": {
                   "code": "RIDE",
                   "name": "Auto Ride"
                 },
                 "fulfillment_ids": [
                   "ae10ca31-d6da-498d-ae67-b1e7aea9523b"
                 ],
                 "price": {
                   "currency": "INR",
                   "value": "210.00",
                   "minimum_value": "190",
                   "maximum_value": "230"
                 },
                 "location_ids": [
                   "d071d9aa-76b6-4041-a860-24f552b22ac2",
                   "f07664e1-e1f9-44c1-8c53-c7755a38fdeb"
                 ]
               },
               {
                 "id": "I3",
                 "descriptor": {
                   "code": "RIDE",
                   "name": "Two Wheeler"
                 },
                 "fulfillment_ids": [
                   "2efcc00a-9ef9-487e-b927-a4d34207de36"
                 ],
                 "price": {
                   "currency": "INR",
                   "value": "210.00",
                   "minimum_value": "190",
                   "maximum_value": "230"
                 },
                 "location_ids": [
                   "af009b52-8a7d-410e-a4c4-80e91785ed55",
                   "13799603-5a65-4cfb-b3d9-86164e07fcc4"
                 ]
               }
             ],
             "locations": [
               {
                 "gps": "12.935549,77.605885",
                 "id": "4eef859d-67c7-4c9a-9739-b3a81aa69c34"
               },
               {
                 "gps": "12.935549,77.605895",
                 "id": "4dfa6bfa-5ccf-492e-b2f8-3bf1939dcd88"
               },
               {
                 "gps": "12.935549,77.605905",
                 "id": "d071d9aa-76b6-4041-a860-24f552b22ac2"
               },
               {
                 "gps": "12.935549,77.605865",
                 "id": "f07664e1-e1f9-44c1-8c53-c7755a38fdeb"
               },
               {
                 "gps": "12.935549,77.605915",
                 "id": "af009b52-8a7d-410e-a4c4-80e91785ed55"
               },
               {
                 "gps": "12.935549,77.605855",
                 "id": "13799603-5a65-4cfb-b3d9-86164e07fcc4"
               }
             ],
             "payments": [
               {
                 "collected_by": "BPP",
                 "tags": [
                   {
                     "descriptor": {
                       "code": "BUYER_FINDER_FEES"
                     },
                     "display": true,
                     "list": [
                       {
                         "descriptor": {
                           "code": "BUYER_FINDER_FEES_PERCENTAGE",
                           "name": "Buyer Finder Fees Percentage"
                         },
                         "value": "1"
                       }
                     ]
                   },
                   {
                     "descriptor": {
                       "code": "SETTLEMENT_TERMS"
                     },
                     "display": false,
                     "list": [
                       {
                         "descriptor": {
                           "code": "SETTLEMENT_WINDOW"
                         },
                         "value": "PT60M"
                       },
                       {
                         "descriptor": {
                           "code": "SETTLEMENT_BASIS"
                         },
                         "value": "DELIVERY"
                       },
                       {
                         "descriptor": {
                           "code": "SETTLEMENT_TYPE"
                         },
                         "value": "UPI"
                       },
                       {
                         "descriptor": {
                           "code": "MANDATORY_ARBITRATION"
                         },
                         "value": "true"
                       },
                       {
                         "descriptor": {
                           "code": "COURT_JURISDICTION"
                         },
                         "value": "New Delhi"
                       },
                       {
                         "descriptor": {
                           "code": "DELAY_INTEREST"
                         },
                         "value": "2.5"
                       },
                       {
                         "descriptor": {
                           "code": "STATIC_TERMS"
                         },
                         "value": "https://example-test-bpp.com/static-terms.txt"
                       }
                     ]
                   }
                 ]
               }
             ]
           }
         ]
       }
     }
   }