{
  "context": {
    "action": "select",
    "bap_id": "backend.choosecabs.com",
    "bap_uri": "https://backend.choosecabs.com/api/trv10",
    "bpp_id": "pramaan.ondc.org/beta/preprod/mock/seller",
    "bpp_uri": "https://pramaan.ondc.org/beta/preprod/mock/seller",
    "domain": "ONDC:TRV10",
    "location": {
      "city": {
        "code": "std:03666"
      },
      "country": {
        "code": "IND"
      }
    },
    "message_id": "012bcb46-e1f1-49af-8354-7bbae875a2ce",
    "timestamp": "2025-01-21T14:05:24.234Z",
    "transaction_id": "02108047-5ba6-489c-ba7a-ab976d0cb09d",
    "ttl": "PT1H",
    "version": "2.0.1"
  },
  "message": {
    "order": {
      "items": [
        {
          "id": "I3"
        }
      ],
      "provider": {
        "id": "OD_101"
      }
    }
  }
}