{
    "context": {
        "domain": "nic2004:52110",
        "country": "IND",
        "city": "std:080",
        "action": "on_update",
        "core_version": "1.0.0",
        "bap_id": "ondc.eunimart.com",
        "bap_uri": "https://ondc.eunimart.com/api/v1/ondc/bap/eunimart_bap/",
        "transaction_id": "760dc49a-4585-4c5c-98d3-d0a8ff0ae2cb",
        "ttl": "PT30S",
        "message_id": "8c25c992-1523-4198-8ad9-c98a84abfd75",
        "timestamp": "2023-01-30T13:42:37.123Z",
        "bpp_id": "kitchens-at.com",
        "bpp_uri": "https://kitchens-at.com/ondc_preprod/Retailer/"
    },
    "message": {
        "order": {
            "id": "a12d70bb-3946-4a88-a306-c7b96aedf9ec",
            "state": null,
            "items": [
                {
                    "id": "2116_72808",
                    "quantity": {
                        "count": 2
                    },
                    "fulfillment_id": "1"
                },
                {
                    "id": "2116_72808",
                    "quantity": {
                        "count": 2
                    },
                    "fulfillment_id": "1",
                    "tags": {
                        "status": "Cancelled"
                    }
                }
            ],
            "quote": {
                "price": {
                    "currency": "INR",
                    "value": "585.5"
                },
                "breakup": [
                    {
                        "price": {
                            "currency": "INR",
                            "value": "510"
                        },
                        "title": "Chicken Noodles (Serves 1)",
                        "@ondc/org/item_id": "2116_72808",
                        "@ondc/org/title_type": "item",
                        "@ondc/org/item_quantity": {
                            "count": "2"
                        },
                        "item": {
                            "price": {
                                "currency": "INR",
                                "value": "255"
                            }
                        }
                    },
                    {
                        "price": {
                            "currency": "INR",
                            "value": "25.5"
                        },
                        "title": "Tax",
                        "@ondc/org/item_id": "2116_72808",
                        "@ondc/org/title_type": "tax"
                    },
                    {
                        "price": {
                            "value": "10",
                            "currency": "INR"
                        },
                        "title": "Packaging Charge",
                        "@ondc/org/item_id": "1",
                        "@ondc/org/title_type": "packing"
                    },
                    {
                        "price": {
                            "value": "40",
                            "currency": "INR"
                        },
                        "title": "Delivery Charge",
                        "@ondc/org/item_id": "1",
                        "@ondc/org/title_type": "delivery"
                    }
                ]
            }
        }
    }
}