{
    "context": {
        "bap_id": "ondc.tummoc.in",
        "bap_uri": "https://stage-dev-api.tummoc.in/ticket/direct/ondc",
        "bpp_id": "pramaan.ondc.org/beta/preprod/mock/seller",
        "bpp_uri": "https://pramaan.ondc.org/beta/preprod/mock/seller",
        "domain": "ONDC:TRV10",
        "location": {
            "city": {
                "code": "std:080"
            },
            "country": {
                "code": "IND"
            }
        },
        "transaction_id": "9b00b468-dc39-466b-8e41-9ee87c98142d",
        "message_id": "dbd00381-38d9-49ee-aeaf-5d5faeca40c8",
        "timestamp": "2025-02-25T06:52:13.033Z",
        "version": "2.0.1",
        "ttl": "PT30S",
        "action": "init"
    },
    "message": {
        "order": {
            "provider": {
                "id": "OD_101"
            },
            "items": [
                {
                    "id": "I1"
                }
            ],
            "fulfillments": [
                {
                    "customer": {
                        "contact": {
                            "phone": "8789012316"
                        },
                        "person": {
                            "name": "Maaz"
                        }
                    },
                    "id": "145e7b72-7cfd-4aa6-93bb-0654210c19d6",
                    "stops": [
                        {
                            "location": {
                                "gps": "13.013520, 13.013520"
                            },
                            "type": "START",
                            "instructions": {
                                "short_desc": "Information about location",
                                "long_desc": "Information about location"
                            }
                        },
                        {
                            "location": {
                                "gps": "12.989667, 77.653630"
                            },
                            "type": "END"
                        }
                    ],
                    "vehicle": {
                        "category": "CAB",
                        "variant": "SUV",
                        "energy_type": "CNG"
                    }
                }
            ],
            "billing": {
                "name": "Maaz",
                "phone": "8789012316",
                "email": "maazdgr6@gmail.com"
            },
            "payments": [
                {
                    "type": "ON-FULFILLMENT",
                    "status": "NOT-PAID",
                    "collected_by": "BPP",
                    "params": {
                        "bank_account_number": "918789012316",
                        "bank_code": "ICIC0001422",
                        "virtual_payment_address": "87890@okicic"
                    },
                    "tags": [
                        {
                            "descriptor": {
                                "code": "BUYER_FINDER_FEES"
                            },
                            "display": false,
                            "list": [
                                {
                                    "descriptor": {
                                        "code": "BUYER_FINDER_FEES_PERCENTAGE"
                                    },
                                    "value": "1"
                                }
                            ]
                        },
                        {
                            "descriptor": {
                                "code": "SETTLEMENT_TERMS"
                            },
                            "display": false,
                            "list": [
                                {
                                    "descriptor": {
                                        "code": "SETTLEMENT_TYPE"
                                    },
                                    "value": "neft"
                                },
                                {
                                    "descriptor": {
                                        "code": "SETTLEMENT_WINDOW"
                                    },
                                    "value": "PT60M"
                                },
                                {
                                    "descriptor": {
                                        "code": "SETTLEMENT_BASIS"
                                    },
                                    "value": "Delivery"
                                },
                                {
                                    "descriptor": {
                                        "code": "MANDATORY_ARBITRATION"
                                    },
                                    "value": "true"
                                },
                                {
                                    "descriptor": {
                                        "code": "COURT_JURISDICTION"
                                    },
                                    "value": "New Delhi"
                                },
                                {
                                    "descriptor": {
                                        "code": "DELAY_INTEREST"
                                    },
                                    "value": "2.5"
                                },
                                {
                                    "descriptor": {
                                        "code": "STATIC_TERMS"
                                    },
                                    "value": "https://www.abc.com/settlement-terms/"
                                },
                                {
                                    "descriptor": {
                                        "code": "SETTLEMENT_AMOUNT"
                                    },
                                    "value": "2.10"
                                }
                            ]
                        }
                    ]
                }
            ]
        }
    }
}