{
  "context": {
    "location": {
      "country": {
        "code": "IND"
      },
      "city": {
        "code": "*"
      }
    },
    "version": "2.0.0",
    "domain": "ONDC:FIS13",
    "action": "select",
    "transaction_id": "7dfd7cc0-7802-4cbd-9b11-2db1ea592de2",
    "message_id": "9c15960c-5706-4280-bed0-26d34e128ff5",
    "timestamp": "2024-05-16T20:07:03.914Z",
    "bap_uri": "https://ondc.sequelstring.com/buyer/protocol",
    "bap_id": "ondc.sequelstring.com/buyer/protocol",
    "ttl": "PT10M",
    "bpp_id": "ondc.sequelstring.com/seller/protocol",
    "bpp_uri": "https://ondc.sequelstring.com/seller/protocol"
  },
  "message": {
    "order": {
      "fulfillments": [
        {
          "customer": {
            "contact": {
              "email": "example@example.com",
              "phone": "1234567890"
            },
            "person": {
              "name": "abhinav"
            }
          }
        }
      ],
      "provider": {
        "id": "P1"
      },
      "items": [
        {
          "id": "M1715889997163",
          "parent_item_id": "I2",
          "add_ons": [
            {
              "id": "C1",
              "quantity": {
                "selected": {
                  "count": 1
                }
              }
            }
          ]
        }
      ]
    }
  }
}