{
    "context": {
        "domain": "ONDC:NTS10",
        "location": {
          "country": {
            "code": "IND"
          },
          "city": {
            "code": "*"
          }
        },
        "version": "2.0.0",
        "action": "on_settle",
        "bap_id": "commonstaging.ipms247.com",
        "bap_uri": "https://commonstaging.ipms247.com/b2bservice/ondc/v1/",
        "bpp_id": "sa_nocs.nbbl.com",
        "bpp_uri": "https://sa_nocs.nbbl.com/nocs_test",
        "transaction_id": "txn-1742477613001",
        "message_id": "msg-1742477613001",
        "timestamp": "2025-03-20T12:2307:05.228Z",
        "ttl": "P1D"
      },
    "message": {
        "settlementType": "NIL"
    }
}