{
    "context": {
        "bap_id": "ondc.tummoc.in",
        "bap_uri": "https://stage-dev-api.tummoc.in/ticket/metro/bookTicket",
        "bpp_id": "ondc-preprod.sequelstring.com/seller/dmrc",
        "bpp_uri": "https://ondc-preprod.sequelstring.com/seller/dmrc",
        "domain": "ONDC:TRV11",
        "location": {
            "city": {
                "code": "std:011"
            },
            "country": {
                "code": "IND"
            }
        },
        "transaction_id": "9acb3eb1-6731-401d-b23c-a5e7e41c4694",
        "message_id": "574999c2-fc6f-4ca4-b8d8-2fe29db33b05",
        "timestamp": "2024-10-01T08:52:55.798Z",
        "version": "2.0.0",
        "ttl": "PT30S",
        "action": "issue"
    },
    "message": {
        "issue": {
            "id": "TMISSUE452603765227195",
            "status": "CLOSED",
            "issue_actions": {
                "complainant_actions": [
                    {
                        "complainant_action": "OPEN",
                        "short_desc": "Ticket not working - due to To & fro mismatch",
                        "updated_at": "2024-10-01T08:52:55.798Z",
                        "updated_by": {
                            "contact": {
                                "email": "srikant@tummoc.com",
                                "phone": "8888888888888"
                            },
                            "org": {
                                "name": "AssistBuddi"
                            },
                            "person": {
                                "name": "Integration User"
                            }
                        }
                    },
                    {
                        "complainant_action": "CLOSE",
                        "short_desc": "Issue Resolved",
                        "updated_at": "2024-10-01T08:52:55.798Z",
                        "updated_by": {
                            "contact": {
                                "email": "srikant@tummoc.com",
                                "phone": "8888888888888"
                            },
                            "org": {
                                "name": "AssistBuddi"
                            },
                            "person": {
                                "name": "Integration User"
                            }
                        }
                    }
                ]
            },
            "created_at": "2024-10-01T08:52:55.798Z",
            "updated_at": "2024-10-01T08:52:55.798Z"
        }
    }
}