{
    "context":{
        "domain":"nic2004:52110",
        "action":"select",
        "country":"IND",
        "city":"std:080",
        "core_version":"1.0.0",
        "bpp_id":"api.test.esamudaay.com/ondc/sdk/bpp/retail/esamudaay",
        "bpp_uri":"https://api.test.esamudaay.com/ondc/sdk/bpp/retail/esamudaay",
        "bap_id":"ondc.meesho.org",
        "bap_uri":"https://ondc.meesho.org/ondc/v1/155210/",
        "transaction_id":"7e3bffb8-0c02-4330-bfc7-14f32a024d26",
        "message_id":"223b45a4-6ebf-4708-94b1-0b439cc25efc",
        "timestamp":"2022-11-14T08:54:40.545Z",
        "ttl":"PT30S"
    },
    "message":{
        "order":{
            "fulfillments":[
                {
                    "end":{
                        "location":{
                            "gps":"12.9714007,77.64559799999999",
                            "address":{
                                "area_code":"560038"
                            }
                        }
                    }
                }
            ],
            "items":[
                {
                    "id":"16364",
                    "location_id":"75e4363f-001b-4519-ace5-28b1f448a0bb",
                    "quantity":{
                        "count":1
                    }
                }
            ],
            "provider":{
                "id":"0635ecff-8fde-4185-8cd8-167efda42bbc",
                "locations":[
                    {
                        "id":"75e4363f-001b-4519-ace5-28b1f448a0bb"
                    }
                ]
            }
        }
    }
}