{
    "context": {
        "domain": "nic2004:60232",
        "country": "IND",
        "city": "std:080",
        "action": "on_init",
        "core_version": "1.1.0",
        "bap_id": "logistics.ondc.digiledge.in",
        "bap_uri": "https://logistics.ondc.digiledge.in",
        "transaction_id": "544d2f58-5c4e-43d5-82d8-aa8923c782d3",
        "message_id": "e01348d6-f1d0-4d07-bc95-853819de0219",
        "timestamp": "2023-09-28T11:10:43.173Z",
        "ttl": "PT30S",
        "bpp_id": "ondc-wrapper-ondc.proxy.dev.dunzo.com",
        "bpp_uri": "https://ondc-wrapper-ondc.proxy.dev.dunzo.com/"
    },
    "message": {
        "order": {
            "items": [
                {
                    "id": "item-14e9ea4d-df37-42ec-87a3-fb7fb5657850"
                }
            ],
            "payment": {
                "type": "POST-FULFILLMENT",
                "@ondc/org/settlement_details": [
                    {
                        "settlement_counterparty": "seller-app",
                        "settlement_type": "neft",
                        "settlement_bank_account_no": "",
                        "settlement_ifsc_code": ""
                    }
                ],
                "collected_by": "BPP"
            },
            "provider": {
                "id": "dunzo-lsp"
            },
            "provider_location": {
                "id": ""
            },
            "quote": {
                "breakup": [
                    {
                        "@ondc/org/item_id": "item-14e9ea4d-df37-42ec-87a3-fb7fb5657850",
                        "@ondc/org/title_type": "Delivery Charge",
                        "price": {
                            "currency": "INR",
                            "value": "391"
                        }
                    }
                ],
                "price": {
                    "currency": "INR",
                    "value": "391"
                }
            }
        }
    }
}