{
    "context": {
        "domain": "nic2004:52110",
        "country": "IND",
        "city": "std:080",
        "core_version": "1.0.0",
        "action": "status",
        "bap_id": "beta.mystore.in",
        "bap_uri": "https://beta.mystore.in/ondc/1.0/",
        "bpp_id": "api.staging.nearshop.in",
        "bpp_uri": "https://api.staging.nearshop.in/bpp/api/v1",
        "transaction_id": "1f49337b-47fc-4a86-b201-22dd0c607997",
        "message_id": "a9176dbd-e77f-49da-89f4-088512835221",
        "timestamp": "2023-01-24T03:31:15.885Z",
        "ttl": "PT30S"
    },
    "message": {
        "order_id": "63cf50f1fcf435aaa54f8dd6"
    }
}