{
    "context": {
        "domain": "ONDC:RET10",
        "country": "IND",
        "city": "*",
        "action": "issue",
        "core_version": "1.0.0",
        "transaction_id": "f1d961ff-793f-4b00-b8a0-dbe2faa2c83a",
        "message_id": "c0a044a4-aea3-43f1-a8c5-6439c17d6204",
        "timestamp": "2023-10-31T04:52:36.899Z",
        "bap_id": "ondcpreprodb2b.rapidor.co",
        "bap_uri": "https://ondcpreprodb2b.rapidor.co/v1/ondc/buyer",
        "bpp_id": "ondcpreprodb2b.rapidor.co",
        "bpp_uri": "https://ondcpreprodb2b.rapidor.co/v1/ondc/seller",
        "ttl": "PT30S"
    },
    "message": {
        "issue": {
            "created_at": "2023-10-31T04:52:36.923Z",
            "updated_at": "2023-10-31T04:52:36.923Z",
            "id": "42fc993e-cdaf-4a8f-969b-7aeb2bdaee95",
            "category": "ITEM",
            "sub_category": "ITM02",
            "complainant_info": {
                "person": {
                    "name": "ABAD FOODS"
                },
                "contact": {
                    "phone": "9072377660",
                    "email": "admin+0710202335@rapidor.co"
                }
            },
            "order_details": {
                "id": "RAP-0040416",
                "state": "confirmed",
                "items": [
                    {
                        "id": "ITM04282",
                        "quantity": 2
                    }
                ],
                "fulfillments": [
                    {
                        "id": "F1"
                    }
                ],
                "provider_id": "abadfoodslive"
            },
            "description": {
                "short_desc": "Quantity issue",
                "long_desc": "Issue Detail",
                "images": [
                    "https://rapidor.s3-us-west-2.amazonaws.com/files/lRrpxWv4cl3F4nbaAUp-0_safeimagekit-dummy-img-100x100-png.png"
                ]
            },
            "source": {
                "network_participant_id": "ondcpreprodb2b.rapidor.co",
                "type": "CONSUMER"
            },
            "expected_response_time": {
                "duration": "PT2H"
            },
            "expected_resolution_time": {
                "duration": "P1D"
            },
            "status": "OPEN",
            "issue_type": "ISSUE",
            "issue_actions": {
                "complainant_actions": [
                    {
                        "complainant_action": "OPEN",
                        "short_desc": "Complaint created",
                        "updated_at": "2023-10-31T04:52:36.923Z",
                        "updated_by": {
                            "org": {
                                "name": "ondcpreprodb2b.rapidor.co::ONDC:RET10"
                            },
                            "contact": {
                                "phone": "8111886544",
                                "email": "care@acelrtech.com"
                            },
                            "person": {
                                "name": "Nyjil Nazeer"
                            }
                        }
                    }
                ]
            }
        }
    }
}