{
    "context": {
        "domain": "ONDC:TRV11",
        "location": {
            "country": {
                "code": "IND"
            },
            "city": {
                "code": "std:011"
            }
        },
        "version": "2.0.0",
        "action": "on_search",
        "transaction_id": "95e1dccb-780f-4ba0-b41d-8f7750ec2e4d",
        "message_id": "dd45e40a-6207-491a-ac76-63ed66c91a95",
        "timestamp": "2024-09-13T11:48:04.347Z",
        "bap_uri": "https://pramaan.ondc.org/beta/preprod/mock/buyer",
        "bap_id": "pramaan.ondc.org/beta/preprod/mock/buyer",
        "ttl": "PT30S",
        "bpp_id": "ondc-preprod.sequelstring.com/seller/dmrc",
        "bpp_uri": "https://ondc-preprod.sequelstring.com/seller/dmrc"
    },
    "message": {
        "catalog": {
            "descriptor": {
                "name": "Delhi Metro Rail Corporation",
                "images": [
                    {
                        "url": "https://delhimetrorail.com/static/media/logo-passenger.d3afd408.svg"
                    }
                ]
            },
            "providers": [
                {
                    "id": "DMRC_5001_1001",
                    "categories": [
                        {
                            "descriptor": {
                                "code": "TICKET",
                                "name": "Ticket"
                            },
                            "id": "C2"
                        }
                    ],
                    "items": [
                        {
                            "id": "18eba05f-5d26-4fbf-b1c5-5346d62e17b0",
                            "category_ids": [
                                "C2"
                            ],
                            "descriptor": {
                                "code": "SJT",
                                "name": "Single Journey Ticket"
                            },
                            "price": {
                                "currency": "INR",
                                "value": "40"
                            },
                            "quantity": {
                                "maximum": {
                                    "count": 8
                                },
                                "minimum": {
                                    "count": 1
                                }
                            },
                            "time": {
                                "label": "Validity",
                                "duration": "PT60M"
                            },
                            "fulfillment_ids": [
                                "c851e50a-6420-45a0-80b1-dcafbcbfd8bd"
                            ]
                        }
                    ],
                    "time": {
                        "range": {
                            "start": "2024-09-13T00:00:00.000Z",
                            "end": "2024-09-13T17:30:00.000Z"
                        }
                    },
                    "descriptor": {
                        "name": "Delhi Metro Rail Corporation",
                        "images": [
                            {
                                "url": "https://delhimetrorail.com/static/media/logo-passenger.d3afd408.svg"
                            }
                        ]
                    },
                    "fulfillments": [
                        {
                            "id": "c851e50a-6420-45a0-80b1-dcafbcbfd8bd",
                            "type": "TRIP",
                            "stops": [
                                {
                                    "location": {
                                        "descriptor": {
                                            "code": "140",
                                            "name": "Belvedere Towers"
                                        },
                                        "gps": "28.492065, 77.088142"
                                    },
                                    "id": "1",
                                    "type": "START"
                                },
                                {
                                    "location": {
                                        "descriptor": {
                                            "code": "139",
                                            "name": "Phase-2"
                                        },
                                        "gps": "28.488371, 77.092865"
                                    },
                                    "id": "2",
                                    "parent_stop_id": "1",
                                    "instructions": {
                                        "name": "Stop 2"
                                    },
                                    "type": "INTERMEDIATE_STOP"
                                },
                                {
                                    "location": {
                                        "descriptor": {
                                            "code": "98",
                                            "name": "Sikandar Pur"
                                        },
                                        "gps": "28.481352, 77.092995"
                                    },
                                    "id": "3",
                                    "parent_stop_id": "2",
                                    "instructions": {
                                        "name": "Stop 3",
                                        "short_desc": "Change here for Yellow Line"
                                    },
                                    "type": "TRANSIT_STOP"
                                },
                                {
                                    "location": {
                                        "descriptor": {
                                            "code": "97",
                                            "name": "Guru DronaCharya"
                                        },
                                        "gps": "28.482075, 77.102219"
                                    },
                                    "id": "4",
                                    "parent_stop_id": "3",
                                    "instructions": {
                                        "name": "Stop 4"
                                    },
                                    "type": "INTERMEDIATE_STOP"
                                },
                                {
                                    "location": {
                                        "descriptor": {
                                            "code": "96",
                                            "name": "Arjan Garh"
                                        },
                                        "gps": "28.480820, 77.125870"
                                    },
                                    "id": "5",
                                    "parent_stop_id": "4",
                                    "instructions": {
                                        "name": "Stop 5"
                                    },
                                    "type": "INTERMEDIATE_STOP"
                                },
                                {
                                    "location": {
                                        "descriptor": {
                                            "code": "95",
                                            "name": "Ghitorny"
                                        },
                                        "gps": "28.493830, 77.149071"
                                    },
                                    "id": "6",
                                    "parent_stop_id": "5",
                                    "instructions": {
                                        "name": "Stop 6"
                                    },
                                    "type": "INTERMEDIATE_STOP"
                                },
                                {
                                    "location": {
                                        "descriptor": {
                                            "code": "94",
                                            "name": "Sultan Pur"
                                        },
                                        "gps": "28.499214, 77.161362"
                                    },
                                    "id": "7",
                                    "parent_stop_id": "6",
                                    "instructions": {
                                        "name": "Stop 7"
                                    },
                                    "type": "INTERMEDIATE_STOP"
                                },
                                {
                                    "location": {
                                        "descriptor": {
                                            "code": "93",
                                            "name": "Chhatar Pur"
                                        },
                                        "gps": "28.506584, 77.174866"
                                    },
                                    "id": "8",
                                    "parent_stop_id": "7",
                                    "instructions": {
                                        "name": "Stop 8"
                                    },
                                    "type": "INTERMEDIATE_STOP"
                                },
                                {
                                    "location": {
                                        "descriptor": {
                                            "code": "92",
                                            "name": "Qutab Minar"
                                        },
                                        "gps": "28.512714, 77.185791"
                                    },
                                    "id": "9",
                                    "parent_stop_id": "8",
                                    "instructions": {
                                        "name": "Stop 9"
                                    },
                                    "type": "INTERMEDIATE_STOP"
                                },
                                {
                                    "location": {
                                        "descriptor": {
                                            "code": "91",
                                            "name": "Saket"
                                        },
                                        "gps": "28.520638, 77.199379"
                                    },
                                    "id": "10",
                                    "parent_stop_id": "9",
                                    "instructions": {
                                        "name": "Stop 10"
                                    },
                                    "type": "INTERMEDIATE_STOP"
                                },
                                {
                                    "location": {
                                        "descriptor": {
                                            "code": "90",
                                            "name": "Malaviya Nagar"
                                        },
                                        "gps": "28.528170, 77.205612"
                                    },
                                    "id": "11",
                                    "parent_stop_id": "10",
                                    "instructions": {
                                        "name": "Stop 11"
                                    },
                                    "type": "INTERMEDIATE_STOP"
                                },
                                {
                                    "location": {
                                        "descriptor": {
                                            "code": "89",
                                            "name": "Hauz Khas"
                                        },
                                        "gps": "28.543346, 77.206673"
                                    },
                                    "id": "12",
                                    "parent_stop_id": "11",
                                    "instructions": {
                                        "name": "Stop 12"
                                    },
                                    "type": "INTERMEDIATE_STOP"
                                },
                                {
                                    "location": {
                                        "descriptor": {
                                            "code": "88",
                                            "name": "Green Park"
                                        },
                                        "gps": "28.559853, 77.206902"
                                    },
                                    "id": "13",
                                    "parent_stop_id": "12",
                                    "instructions": {
                                        "name": "Stop 13"
                                    },
                                    "type": "INTERMEDIATE_STOP"
                                },
                                {
                                    "location": {
                                        "descriptor": {
                                            "code": "87",
                                            "name": "AIIMS"
                                        },
                                        "gps": "28.568199, 77.207947"
                                    },
                                    "id": "14",
                                    "parent_stop_id": "13",
                                    "type": "END"
                                }
                            ],
                            "vehicle": {
                                "category": "METRO"
                            }
                        }
                    ],
                    "payments": [
                        {
                            "collected_by": "BAP",
                            "tags": [
                                {
                                    "descriptor": {
                                        "code": "BUYER_FINDER_FEES"
                                    },
                                    "display": false,
                                    "list": [
                                        {
                                            "descriptor": {
                                                "code": "BUYER_FINDER_FEES_PERCENTAGE"
                                            },
                                            "value": "1"
                                        },
                                        {
                                            "descriptor": {
                                                "code": "BUYER_FINDER_FEES_TYPE"
                                            },
                                            "value": "percent"
                                        }
                                    ]
                                },
                                {
                                    "descriptor": {
                                        "code": "SETTLEMENT_TERMS"
                                    },
                                    "display": false,
                                    "list": [
                                        {
                                            "descriptor": {
                                                "code": "SETTLEMENT_WINDOW"
                                            },
                                            "value": "P1D"
                                        },
                                        {
                                            "descriptor": {
                                                "code": "SETTLEMENT_BASIS"
                                            },
                                            "value": "INVOICE_RECEIPT"
                                        },
                                        {
                                            "descriptor": {
                                                "code": "MANDATORY_ARBITRATION"
                                            },
                                            "value": "true"
                                        },
                                        {
                                            "descriptor": {
                                                "code": "COURT_JURISDICTION"
                                            },
                                            "value": "New Delhi"
                                        },
                                        {
                                            "descriptor": {
                                                "code": "STATIC_TERMS"
                                            },
                                            "value": "https://delhimetrorail.com/faq-tickets-fare"
                                        },
                                        {
                                            "descriptor": {
                                                "code": "DELAY_INTEREST"
                                            },
                                            "value": "2.5"
                                        }
                                    ]
                                }
                            ]
                        }
                    ],
                    "tags": [
                        {
                            "descriptor": {
                                "code": "SCHEDULED_INFO"
                            },
                            "display": false,
                            "list": [
                                {
                                    "descriptor": {
                                        "code": "GTFS"
                                    },
                                    "value": "https://otd.delhi.gov.in/data/staticDMRC/"
                                }
                            ]
                        }
                    ]
                }
            ]
        }
    }
}