{
  "context": {
    "country": "IND",
    "bpp_uri": "https://mobilityseller.sumasoft.com/mobility/auto",
    "domain": "ONDC:TRV10",
    "timestamp": "2023-12-14T10:58:57.785Z",
    "bap_id": "mobilitybuyer.sumasoft.com",
    "transaction_id": "5f2be493-63c4-4496-90c1-a632a8e79791",
    "bpp_id": "mobilityseller.sumasoft.com",
    "message_id": "abf5b5d0-fb9d-4fd3-a689-895bdd59507e",
    "core_version": "1.0.0",
    "action": "get_feedback_categories",
    "bap_uri": "https://mobilitybuyer.sumasoft.com/mobility/passenger"
  }
}