{
    "context": {
        "domain": "ONDC:RET14",
        "country": "IND",
        "city": "std:080",
        "action": "select",
        "core_version": "1.1.0",
        "bap_id": "b2bapi-stage.spicesmartshop.com",
        "bap_uri": "https://b2bapi-stage.spicesmartshop.com/bap",
        "bpp_id": "b-spicemoneyondc.nlincs.in",
        "bpp_uri": "https://b-spicemoneyondc.nlincs.in/bpp",
        "transaction_id": "7dc8fc42-653c-4893-8710-385cd62e278b",
        "message_id": "0ccddc98-4261-4a55-9660-6817428329e8",
        "timestamp": "2023-04-25T12:22:16.516Z",
        "ttl": "PT30S"
    },
    "message": {
        "order": {
            "provider": {
                "id": "21045"
            },
            "items": [
                {
                    "id": "AEP-24",
                    "quantity": {
                        "count": 9
                    }
                },
                {
                    "id": "RWE-308",
                    "quantity": {
                        "count": 5
                    }
                }
            ],
            "fulfillments": [
                {
                    "end": {
                        "location": {
                            "gps": "12.972442 ,77.580643",
                            "address": {
                                "area_code": "560027"
                            }
                        }
                    }
                }
            ],
            "payment": {
                "type": "ON-ORDER"
            },
            "tags": [
                {
                    "code": "buyer_id",
                    "list": [
                        {
                            "code": "buyer_id_code",
                            "value": "gst"
                        },
                        {
                            "code": "buyer_id_no",
                            "value": "GSTIN271196"
                        }
                    ]
                }
            ]
        }
    }
}
