{
  "context": {
    "domain": "ONDC:FIS12",
    "location": {
      "country": {
        "code": "IND"
      },
      "city": {
        "code": "*"
      }
    },
    "version": "2.1.0",
    "action": "search",
    "bap_id": "ondc.invoicepe.in",
    "bap_uri": "https://ondc.invoicepe.in/financial-services/invoice-based-credit",
    "transaction_id": "a4ab553c-ba15-4923-ab0c-6255a87d0860",
    "message_id": "5bc1a66d-91a0-49db-a26b-4bdde180e39f",
    "ttl": "PT90M",
    "timestamp": "2024-12-05T04:22:56.698Z",
    "bpp_id": "ondc.bpp.fis12.invoicepe.in",
    "bpp_uri": "https://ondc.bpp.fis12.invoicepe.in/invoice-based-credit"
  },
  "message": {
    "intent": {
      "category": {
        "descriptor": {
          "code": "INVOICE_BASED_LOAN"
        }
      },
      "provider": {
        "id": "8882ba72-919f-4db3-8121-8540130a6dec",
        "items": [
          {
            "id": "8622f4ec-50db-4374-9bdd-9ef0a6fc4d49",
            "xinput": {
              "form": {
                "id": "a7a83363-c5e9-4ee8-9089-caa887a17bf4"
              },
              "form_response": {
                "status": "APPROVED",
                "submission_id": "db68ca5d-dbd1-446b-b426-122ccdf5c306"
              }
            }
          }
        ]
      },
      "payment": {
        "collected_by": "BPP",
        "tags": [
          {
            "descriptor": {
              "code": "BUYER_FINDER_FEES"
            },
            "list": [
              {
                "descriptor": {
                  "code": "BUYER_FINDER_FEES_TYPE"
                },
                "value": "PERCENT-ANNUALIZED"
              },
              {
                "descriptor": {
                  "code": "BUYER_FINDER_FEES_PERCENTAGE"
                },
                "value": "1"
              }
            ],
            "display": false
          },
          {
            "descriptor": {
              "code": "SETTLEMENT_TERMS"
            },
            "list": [
              {
                "descriptor": {
                  "code": "DELAY_INTEREST"
                },
                "value": "2.5"
              },
              {
                "descriptor": {
                  "code": "STATIC_TERMS"
                },
                "value": "https://bap.credit.becknprotocol.io/business-banking/loans/invoice-based-loan"
              },
              {
                "descriptor": {
                  "code": "OFFLINE_CONTRACT"
                },
                "value": "true"
              }
            ],
            "display": false
          }
        ]
      }
    }
  }
}